YouTubeTranscript/__init__.py
YouTubeTranscript-1.0.dist-info/LICENSE
YouTubeTranscript-1.0.dist-info/METADATA
YouTubeTranscript-1.0.dist-info/WHEEL
YouTubeTranscript-1.0.dist-info/top_level.txt
YouTubeTranscript-1.0.dist-info/RECORD
