Metadata-Version: 2.1
Name: YouTubeTranscript
Version: 1.0
Summary: YouTube Transcript Downloader
Home-page: https://github.com/dannybritto96/YouTubeTranscript
Author: Danie Britto
Author-email: danieb1996@live.com
License: UNKNOWN
Platform: UNKNOWN
Classifier: Programming Language :: Python :: 3
Classifier: License :: OSI Approved :: MIT License
Classifier: Operating System :: OS Independent
Requires-Dist: youtube-dl
Requires-Dist: bs4
Requires-Dist: requests
